[
  {
    "name": "Hackaday",
    "url": "https://hackaday.com/blog/feed/",
    "category": "DIY / Electronics",
    "ok": true,
    "count": 7,
    "visible": 7,
    "max_items": 7,
    "favorite": false
  },
  {
    "name": "BearBlog",
    "url": "https://bearblog.dev/discover/feed/",
    "category": "Blogs",
    "ok": true,
    "count": 20,
    "visible": 7,
    "max_items": 7,
    "favorite": true
  },
  {
    "name": "Plan D",
    "url": "https://www.youtube.com/feeds/videos.xml?channel_id=UCPaApoLkmPqxCeZF7gjoc3w",
    "category": "YouTube",
    "ok": true,
    "count": 15,
    "visible": 7,
    "max_items": 7,
    "favorite": false
  },
  {
    "name": "Hacker News",
    "url": "https://news.ycombinator.com/rss",
    "category": "Technology",
    "ok": true,
    "count": 30,
    "visible": 7,
    "max_items": 7,
    "favorite": true
  }
]
